plotverse/__init__.py
plotverse/core/__init__.py
plotverse-0.0.9.dist-info/METADATA
plotverse-0.0.9.dist-info/WHEEL
plotverse-0.0.9.dist-info/top_level.txt
plotverse-0.0.9.dist-info/RECORD
